fed_rf_mk/__init__.py
fed_rf_mk/client.py
fed_rf_mk/datasets.py
fed_rf_mk/datasites.py
fed_rf_mk/remote_tasks.py
fed_rf_mk/server.py
fed_rf_mk/utils.py
fed_rf_mk/aggregation/__init__.py
fed_rf_mk/aggregation/models.py
fed_rf_mk/handlers/__init__.py
fed_rf_mk/handlers/pfi.py
fed_rf_mk/handlers/shap.py
fed_rf_mk/orchestrator/__init__.py
fed_rf_mk/orchestrator/clients.py
fed_rf_mk/orchestrator/weights.py
fed_rf_mk-1.0.0.dist-info/licenses/LICENSE
fed_rf_mk-1.0.0.dist-info/METADATA
fed_rf_mk-1.0.0.dist-info/WHEEL
fed_rf_mk-1.0.0.dist-info/entry_points.txt
fed_rf_mk-1.0.0.dist-info/top_level.txt
fed_rf_mk-1.0.0.dist-info/RECORD
